[
  {
    "id": "924590bc99ebf6cc",
    "itemUrl": "https://item.rakuten.co.jp/kensho-yame/item17/?variantId=item-9",
    "itemName": "青汁 緑茶 青汁緑茶 120g 送料無料 約120杯分 九州産 大麦若葉 抹茶 無着色 子供 美容 健康 粉末 飲みやすい お手軽 美味しい 栄養補給 食物繊維 お子様に ラテ 青汁ラテ ホット アイス 水だし お湯だし 自社生産 メール便",
    "shopName": "健祥GW 楽天市場店",
    "imageUrl": "https://thumbnail.image.rakuten.co.jp/@0_mall/kensho-yame/cabinet/ef/item/2509_aojirutea_kago.jpg?_ex=600x600",
    "genre": "other",
    "currentPrice": 1000,
    "originalPrice": null,
    "discountPercent": 0,
    "pointRate": 46,
    "pointAmount": 463,
    "isSuperDeal": true,
    "reviewCount": 1097,
    "reviewAverage": 4.66,
    "dealEndTime": "2026-07-06T23:59:59.000+09:00",
    "scrapedAt": "2026-07-01T08:51:42.541Z",
    "sourcePage": "superdeal",
    "isSoldOut": false
  },
  {
    "id": "5d4d7101e6d46eb0",
    "itemUrl": "https://item.rakuten.co.jp/shokunohakobune/fmix800-1-rs/",
    "itemName": "6種ミックス 700g ミックスナッツ フルーツ入り 種類が選べる メープルくるみ 黒糖くるみ 無添加 無塩 アーモンド くるみ カシューナッツ ドライフルーツ バナナ 無花果 ミックス 健康 おやつ おつまみ 送料無料 R--",
    "shopName": "食はこ 楽天市場店",
    "imageUrl": "https://thumbnail.image.rakuten.co.jp/@0_mall/shokunohakobune/cabinet/06336114/08685865/09893907/imgrc0127701011.jpg?_ex=600x600",
    "genre": "other",
    "currentPrice": 2960,
    "originalPrice": null,
    "discountPercent": 0,
    "pointRate": 46,
    "pointAmount": 1370,
    "isSuperDeal": true,
    "reviewCount": 676,
    "reviewAverage": 4.52,
    "dealEndTime": null,
    "scrapedAt": "2026-07-01T08:51:42.540Z",
    "sourcePage": "superdeal",
    "isSoldOut": false
  },
  {
    "id": "4bb42684cbbeb171",
    "itemUrl": "https://item.rakuten.co.jp/matsushimakakiya/namasyoku-4k-ss/?variantId=normal-inventory",
    "itemName": "牡蠣 殻付き 生牡蠣 「生食用 殻付き 牡蠣 4kg」 （28~70粒）貝類 貝 kaki oyster オイスター4キロ 牡蠣 殻付き 牡蛎 牡蠣 殻付 宮城県産 カキ 松島牡蠣屋 【100】",
    "shopName": "松島牡蠣屋",
    "imageUrl": "https://thumbnail.image.rakuten.co.jp/@0_mall/matsushimakakiya/cabinet/04355508/04355529/imgrc0091294067.jpg?_ex=600x600",
    "genre": "thuc_pham",
    "currentPrice": 9960,
    "originalPrice": null,
    "discountPercent": 0,
    "pointRate": 46,
    "pointAmount": 4611,
    "isSuperDeal": true,
    "reviewCount": 146,
    "reviewAverage": 4.32,
    "dealEndTime": null,
    "scrapedAt": "2026-07-01T08:51:51.887Z",
    "sourcePage": "superdeal",
    "isSoldOut": false
  },
  {
    "id": "1dc50f97a1e1c730",
    "itemUrl": "https://item.rakuten.co.jp/ekiichi/e750-019/",
    "itemName": "【期間限定 50％ポイント還元中！さらにお得クーポンも発行！】 安納芋蜜フィナンシェ バラタイプ 4〜8個 ギフト 個包装 お中元 鹿児島県 お中元 職場 同僚 取引先 産地直送 お取り寄せ ギフト プレゼント 贈り物 送料無料",
    "shopName": "薩摩川内Webショップ『薩摩國』",
    "imageUrl": "https://thumbnail.image.rakuten.co.jp/@0_gold/ekiichi/750/imofinanshebarasku_00_1000x1000_w.jpg?_ex=600x600",
    "genre": "other",
    "currentPrice": 1593,
    "originalPrice": null,
    "discountPercent": 0,
    "pointRate": 46,
    "pointAmount": 737,
    "isSuperDeal": true,
    "reviewCount": 109,
    "reviewAverage": 4.63,
    "dealEndTime": null,
    "scrapedAt": "2026-07-01T08:51:48.416Z",
    "sourcePage": "superdeal",
    "isSoldOut": false
  },
  {
    "id": "1b15f236d17e2d11",
    "itemUrl": "https://item.rakuten.co.jp/r-food/rf-d-00198/",
    "itemName": "【A配送】テオブロマ ミニキャビア ギフト 洋菓子 詰め合わせ 贈り物 プレゼント チョコ 缶 お菓子 おしゃれ かわいい 送料無料 チョコレート スイーツ プチギフト 土屋シェフ お返し 高級",
    "shopName": "Rakuten グルメ館",
    "imageUrl": "https://thumbnail.image.rakuten.co.jp/@0_mall/r-food/cabinet/theobroma/item_mc2025_img01.jpg?_ex=600x600",
    "genre": "other",
    "currentPrice": 8990,
    "originalPrice": null,
    "discountPercent": 0,
    "pointRate": 46,
    "pointAmount": 4162,
    "isSuperDeal": true,
    "reviewCount": 69,
    "reviewAverage": 4.3,
    "dealEndTime": "2026-07-01T23:59:59.000+09:00",
    "scrapedAt": "2026-07-01T08:51:48.416Z",
    "sourcePage": "superdeal",
    "isSoldOut": false
  },
  {
    "id": "f96f693251aa6786",
    "itemUrl": "https://item.rakuten.co.jp/norton/21435750/?variantId=21435750",
    "itemName": "ノートン norton ノートン360 プレミアム 5台 3年版 ダウンロード iOS windows mac セキュリティソフト 送料無料 セキュリティ ウイルス対策 pc iphone ipad アイフォン タブレット ネットワーク",
    "shopName": "ノートン公式ストア 楽天市場店",
    "imageUrl": "https://thumbnail.image.rakuten.co.jp/@0_mall/norton/cabinet/08738151/13252211/n360_premium_5-3.jpg?_ex=600x600",
    "genre": "other",
    "currentPrice": 16980,
    "originalPrice": null,
    "discountPercent": 0,
    "pointRate": 45,
    "pointAmount": 7718,
    "isSuperDeal": true,
    "reviewCount": 451,
    "reviewAverage": 4.4,
    "dealEndTime": null,
    "scrapedAt": "2026-07-01T08:51:42.540Z",
    "sourcePage": "superdeal",
    "isSoldOut": false
  },
  {
    "id": "1a742d273bf2d4df",
    "itemUrl": "https://item.rakuten.co.jp/myhomeshop/gy-txd/?variantId=gy-txd",
    "itemName": "シェーバー メンズ 髭剃り トリマー 電気シェーバー ボディシェーバー 電動バリカン USB充電式 ヘアカッター ヒゲトリマー 全身 お風呂剃り可 水洗い可 メンズ 除毛 男性 シェーバー メンズ ひげトリマー 防水",
    "shopName": "My Home Shop 日用品楽天市場店",
    "imageUrl": "https://thumbnail.image.rakuten.co.jp/@0_mall/myhomeshop/cabinet/10165787/11973658/1.jpg?_ex=600x600",
    "genre": "other",
    "currentPrice": 7860,
    "originalPrice": null,
    "discountPercent": 0,
    "pointRate": 45,
    "pointAmount": 3573,
    "isSuperDeal": true,
    "reviewCount": 269,
    "reviewAverage": 4.36,
    "dealEndTime": null,
    "scrapedAt": "2026-07-01T08:51:51.887Z",
    "sourcePage": "superdeal",
    "isSoldOut": false
  },
  {
    "id": "368521e1e06defd1",
    "itemUrl": "https://item.rakuten.co.jp/cecs2022/zwj70/",
    "itemName": "【クーポンで最大1000円OFF】排気口カバー 60cm 75cm フラットタイプ 奥行伸縮 コンロ 排気口カバー ih 排気口カバー スマート グリルカバー コンロ奥カバー＆ラック 油はねカバー 油汚れ グリル排気口カバー コンロ奥 掃除 黒 白 ブラック シルバー",
    "shopName": "CECS楽天市場店",
    "imageUrl": "https://thumbnail.image.rakuten.co.jp/@0_mall/cecs2022/cabinet/09788447/11167947/zwj.jpg?_ex=600x600",
    "genre": "other",
    "currentPrice": 4199,
    "originalPrice": null,
    "discountPercent": 0,
    "pointRate": 45,
    "pointAmount": 1909,
    "isSuperDeal": true,
    "reviewCount": 135,
    "reviewAverage": 4.54,
    "dealEndTime": null,
    "scrapedAt": "2026-07-01T08:51:48.416Z",
    "sourcePage": "superdeal",
    "isSoldOut": false
  },
  {
    "id": "d88924796a828609",
    "itemUrl": "https://item.rakuten.co.jp/irisplaza-r/7176100/?variantId=7176100",
    "itemName": "＼50%ポイントバック☆彡〜7/2 9:59迄／ティッシュ 60パック ソフトパックティッシュ ティッシュペーパー ティシュ— 300枚 150組 60個 5個入り×12袋セット 伊藤忠紙パルプ【iris_dl03】",
    "shopName": "アイリスオーヤマ公式 楽天市場店",
    "imageUrl": "https://thumbnail.image.rakuten.co.jp/@0_mall/irisplaza-r/cabinet/10172579/imgrc0110231848.jpg?_ex=600x600",
    "genre": "other",
    "currentPrice": 6580,
    "originalPrice": null,
    "discountPercent": 0,
    "pointRate": 45,
    "pointAmount": 2991,
    "isSuperDeal": true,
    "reviewCount": 110,
    "reviewAverage": 4.49,
    "dealEndTime": null,
    "scrapedAt": "2026-07-01T08:51:42.541Z",
    "sourcePage": "superdeal",
    "isSoldOut": false
  },
  {
    "id": "380c4b011e35ca15",
    "itemUrl": "https://item.rakuten.co.jp/superdeal/12910ae52002307/?variantId=12910ae52002307",
    "itemName": "【着後レビューで300円クーポンGET！】貝印 関孫六 ダマスカス 三徳包丁 165mm AE5200",
    "shopName": "楽天スーパーDEALSHOP",
    "imageUrl": "https://thumbnail.image.rakuten.co.jp/@0_mall/superdeal/cabinet/09061004/10528769/10952437/imgrc0330040287.jpg?_ex=600x600",
    "genre": "other",
    "currentPrice": 16800,
    "originalPrice": null,
    "discountPercent": 0,
    "pointRate": 41,
    "pointAmount": 6872,
    "isSuperDeal": true,
    "reviewCount": 118,
    "reviewAverage": 4.76,
    "dealEndTime": "2026-07-03T09:59:59.000+09:00",
    "scrapedAt": "2026-07-01T08:52:04.878Z",
    "sourcePage": "superdeal",
    "isSoldOut": false
  },
  {
    "id": "e494a06397d17bcb",
    "itemUrl": "https://item.rakuten.co.jp/d-fit/03952/",
    "itemName": "【★40％ポイントバック 7/2 9:59 迄】歯ブラシ 子供 まとめ買い キャラクター子ども歯ブラシ30本 (トミカ・キティ・ドラえもん・シナモロール・なまえ・スヌーピー・最強王図鑑) (メール便2点まで) 【メール便選択で送料無料】",
    "shopName": "歯科医院専売品のデンタルフィット",
    "imageUrl": "https://thumbnail.image.rakuten.co.jp/@0_mall/d-fit/cabinet/itemimg01/03952_sam04.jpg?_ex=600x600",
    "genre": "other",
    "currentPrice": 4180,
    "originalPrice": null,
    "discountPercent": 0,
    "pointRate": 36,
    "pointAmount": 1520,
    "isSuperDeal": true,
    "reviewCount": 3861,
    "reviewAverage": 4.77,
    "dealEndTime": null,
    "scrapedAt": "2026-07-01T08:51:58.924Z",
    "sourcePage": "superdeal",
    "isSoldOut": false
  },
  {
    "id": "d3e05537c89d7aaa",
    "itemUrl": "https://item.rakuten.co.jp/rakuten24/404954/",
    "itemName": "【1種類を選べる】フレア フレグランス IROKA 柔軟剤 詰め替え(650ml×5袋入)【フレアフレグランスIROKA】",
    "shopName": "楽天24",
    "imageUrl": "https://thumbnail.image.rakuten.co.jp/@0_mall/rakuten24/cabinet/954/404954.jpg?_ex=600x600",
    "genre": "other",
    "currentPrice": 5280,
    "originalPrice": null,
    "discountPercent": 0,
    "pointRate": 36,
    "pointAmount": 1920,
    "isSuperDeal": true,
    "reviewCount": 1597,
    "reviewAverage": 4.75,
    "dealEndTime": null,
    "scrapedAt": "2026-07-01T08:51:58.924Z",
    "sourcePage": "superdeal",
    "isSoldOut": false
  },
  {
    "id": "2b837f9573e036df",
    "itemUrl": "https://item.rakuten.co.jp/hopnic/xst-10b_01/",
    "itemName": "夜間 運転 サングラス メンズ レディース 偏光サングラス 偏光 オーバーグラス メガネの上から ナイト ドライブサングラス メラニン UVカット 夜釣り 夜 メガネ 鯖江 遮光 眼鏡 オーバーサングラス 花粉症 花粉 保護メガネ ナイトライダー サングラス",
    "shopName": "鯖江のサングラス専門店ヒトミケア",
    "imageUrl": "https://thumbnail.image.rakuten.co.jp/@0_mall/hopnic/cabinet/sc50k-car-y75/sc50-20260422-21.jpg?_ex=600x600",
    "genre": "other",
    "currentPrice": 8990,
    "originalPrice": null,
    "discountPercent": 0,
    "pointRate": 36,
    "pointAmount": 3269,
    "isSuperDeal": true,
    "reviewCount": 75,
    "reviewAverage": 4.24,
    "dealEndTime": null,
    "scrapedAt": "2026-07-01T08:52:04.878Z",
    "sourcePage": "superdeal",
    "isSoldOut": false
  },
  {
    "id": "1092d2d100fbb0d3",
    "itemUrl": "https://item.rakuten.co.jp/aideall/s-yz-968/",
    "itemName": "★限定P40倍→2533円★ホットアイマスク USB 充電式 マスク アイピロー アイ グッズ 目 男女兼用 遮光 温め 冷感 振動 快適 リラックス 目元 フィット 旅行 プレゼント ブラック グレー アイケア 睡眠 安眠 便利 トラベル 疲れ 持ち運び 女性 男性 軽量 健康 ギフト",
    "shopName": "aideall",
    "imageUrl": "https://thumbnail.image.rakuten.co.jp/@0_mall/aideall/cabinet/10896179/12170642/00-1.jpg?_ex=600x600",
    "genre": "other",
    "currentPrice": 3980,
    "originalPrice": null,
    "discountPercent": 0,
    "pointRate": 36,
    "pointAmount": 1447,
    "isSuperDeal": true,
    "reviewCount": 70,
    "reviewAverage": 4.64,
    "dealEndTime": null,
    "scrapedAt": "2026-07-01T08:51:58.924Z",
    "sourcePage": "superdeal",
    "isSoldOut": false
  },
  {
    "id": "51018b5fad659e09",
    "itemUrl": "https://item.rakuten.co.jp/beneru/lh2024/?variantId=B1LH2024B",
    "itemName": "35%POINTBACKで6,130円【楽天1位】 加湿器 大容量 加湿器 卓上 6L 加湿機 ハイブリッド加湿器 加湿器 スチーム式 四重除菌 空気清浄機 卓上 オフィス 湿度設定 イオン除菌 UVライト除菌 高温除菌 超音波加熱式 次亜塩素酸水対応 アロマ対応 切タイマー設定 父の日",
    "shopName": "BeniLeaf",
    "imageUrl": "https://thumbnail.image.rakuten.co.jp/@0_mall/beneru/cabinet/lp2209b/lp2209_main-b2.jpg?_ex=600x600",
    "genre": "other",
    "currentPrice": 8990,
    "originalPrice": null,
    "discountPercent": 0,
    "pointRate": 32,
    "pointAmount": 2860,
    "isSuperDeal": true,
    "reviewCount": 999,
    "reviewAverage": 4.33,
    "dealEndTime": null,
    "scrapedAt": "2026-07-01T08:52:12.859Z",
    "sourcePage": "superdeal",
    "isSoldOut": false
  }
]